COPYING
MANIFEST.in
README.rst
config.ini.example
setup.py
asterisk_mbox_server/__init__.py
asterisk_mbox_server/cdr.py
asterisk_mbox_server/mbox.py
asterisk_mbox_server.egg-info/PKG-INFO
asterisk_mbox_server.egg-info/SOURCES.txt
asterisk_mbox_server.egg-info/dependency_links.txt
asterisk_mbox_server.egg-info/entry_points.txt
asterisk_mbox_server.egg-info/requires.txt
asterisk_mbox_server.egg-info/top_level.txt