Metadata-Version: 1.0
Name: asterisk-mbox-server
Version: 0.5.0
Summary: The server portion of a client/server to interact with Asterisk voicemail mailboxes
Home-page: https://github.com/PhracturedBlue/asterisk_mbox_server
Author: PhracturedBlue
Author-email: rc2012@pblue.org
License: UNKNOWN
Keywords: testing,asteriskmailbox,voicemail
Platform: UNKNOWN
